<?xml version="1.0" encoding="utf-8"?>
<publishData>
  <publishProfile publishUrl="C:\BuscadorConcursarDeploy" deleteExistingFiles="False" ftpAnonymousLogin="False" ftpPassiveMode="True" msdeploySite="" msdeploySiteID="" msdeployRemoteSitePhysicalPath="" msdeployAllowUntrustedCertificate="False" msdeploySkipExtraFilesOnServer="True" msdeployMarkAsApp="False" profileName="Perfil1" publishMethod="FileSystem" replaceMatchingFiles="True" userName="" savePWD="False" userPWD="" SelectedForPublish="True">
    <file relUrl="Web.config" publishTime="06/30/2015 20:43:06" />
    <file relUrl="WebForm1.aspx" publishTime="06/23/2015 22:05:41" />
    <file relUrl="buscador012015.html" publishTime="06/30/2015 19:23:10" />
    <file relUrl="bin/BuscadorConcursar.pdb" publishTime="06/30/2015 20:49:36" />
    <file relUrl="buscador.css" publishTime="06/23/2015 22:05:41" />
    <file relUrl="jquery-1.11.1.min.js" publishTime="06/23/2015 22:05:41" />
    <file relUrl="listadodeactas.html" publishTime="06/23/2015 22:05:41" />
    <file relUrl="list.js" publishTime="06/23/2015 22:05:41" />
    <file relUrl="bin/BuscadorConcursar.dll" publishTime="06/30/2015 20:49:37" />
    <file relUrl="bin/Newtonsoft.Json.dll" publishTime="06/23/2015 22:05:41" />
    <file relUrl="json3.min.js" publishTime="06/23/2015 22:05:41" />
    <file relUrl="index.html" publishTime="06/26/2015 18:37:14" />
    <file relUrl="BuscadorSrv.asmx" publishTime="06/23/2015 22:05:41" />
    <file relUrl="listadodeactas.css" publishTime="06/23/2015 22:05:41" />
  </publishProfile>
</publishData>